ssb_pypi_test_srf/__init__.py
ssb_pypi_test_srf/__main__.py
ssb_pypi_test_srf/functions.py
ssb_pypi_test_srf/py.typed
ssb_pypi_test_srf-0.0.2.dist-info/LICENSE
ssb_pypi_test_srf-0.0.2.dist-info/METADATA
ssb_pypi_test_srf-0.0.2.dist-info/WHEEL
ssb_pypi_test_srf-0.0.2.dist-info/entry_points.txt
ssb_pypi_test_srf-0.0.2.dist-info/RECORD
