Metadata-Version: 2.3
Name: ssb-pypi-test-srf
Version: 0.0.2
Summary: SSB Pypi Test Srf
License: MIT
Author: srf@ssb.no
Author-email: srf@ssb.no
Requires-Python: >=3.10,<4.0
Classifier: Development Status :: 4 - Beta
Classifier: License :: OSI Approved :: MIT License
Classifier: Programming Language :: Python :: 3
Classifier: Programming Language :: Python :: 3.10
Classifier: Programming Language :: Python :: 3.11
Classifier: Programming Language :: Python :: 3.12
Classifier: Programming Language :: Python :: 3.13
Requires-Dist: click (>=8.0.1)
Project-URL: Changelog, https://github.com/statisticsnorway/ssb-pypi-test-srf/releases
Project-URL: Documentation, https://statisticsnorway.github.io/ssb-pypi-test-srf
Project-URL: Homepage, https://github.com/statisticsnorway/ssb-pypi-test-srf
Project-URL: Repository, https://github.com/statisticsnorway/ssb-pypi-test-srf
